{
  "update": "202503162311",
  "game_version": "Gold_Silver_Crystal",
  "waza_machine": {
    "わざマシン1": "ばくれつパンチ",
    "わざマシン2": "ずつき",
    "わざマシン3": "のろい",
    "わざマシン4": "ころがる",
    "わざマシン5": "ほえる",
    "わざマシン6": "どくどく",
    "わざマシン7": "でんじほう",
    "わざマシン8": "いわくだき",
    "わざマシン9": "じこあんじ",
    "わざマシン10": "めざめるパワー",
    "わざマシン11": "にほんばれ",
    "わざマシン12": "あまいかおり",
    "わざマシン13": "いびき",
    "わざマシン14": "ふぶき",
    "わざマシン15": "はかいこうせん",
    "わざマシン16": "こごえるかぜ",
    "わざマシン17": "まもる",
    "わざマシン18": "あまごい",
    "わざマシン19": "ギガドレイン",
    "わざマシン20": "こらえる",
    "わざマシン21": "やつあたり",
    "わざマシン22": "ソーラービーム",
    "わざマシン23": "アイアンテール",
    "わざマシン24": "りゅうのいぶき",
    "わざマシン25": "かみなり",
    "わざマシン26": "じしん",
    "わざマシン27": "おんがえし",
    "わざマシン28": "あなをほる",
    "わざマシン29": "サイコキネシス",
    "わざマシン30": "シャドーボール",
    "わざマシン31": "どろかけ",
    "わざマシン32": "かげぶんしん",
    "わざマシン33": "れいとうパンチ",
    "わざマシン34": "いばる",
    "わざマシン35": "ねごと",
    "わざマシン36": "ヘドロばくだん",
    "わざマシン37": "すなあらし",
    "わざマシン38": "だいもんじ",
    "わざマシン39": "スピードスター",
    "わざマシン40": "まるくなる",
    "わざマシン41": "かみなりパンチ",
    "わざマシン42": "ゆめくい",
    "わざマシン43": "みきり",
    "わざマシン44": "ねむる",
    "わざマシン45": "メロメロ",
    "わざマシン46": "どろぼう",
    "わざマシン47": "はがねのつばさ",
    "わざマシン48": "ほのおのパンチ",
    "わざマシン49": "れんぞくぎり",
    "わざマシン50": "あくむ"
  }
}
